LDtools/__init__.py
LDtools/_nbdev.py
LDtools/genodata.py
LDtools/ldmatrix.py
LDtools/liftover.py
LDtools/sumstat.py
LDtools/utils.py
LDtoolsets-0.0.14.dist-info/LICENSE
LDtoolsets-0.0.14.dist-info/METADATA
LDtoolsets-0.0.14.dist-info/WHEEL
LDtoolsets-0.0.14.dist-info/entry_points.txt
LDtoolsets-0.0.14.dist-info/top_level.txt
LDtoolsets-0.0.14.dist-info/RECORD
