Metadata-Version: 2.1
Name: LDtoolsets
Version: 0.0.14
Summary: Modules for LD computing, liftover and region extraction
Home-page: https://github.com/changebio/LDtools/tree/master/
Author: YinHuang
Author-email: changebio@yeah.net
License: Apache Software License 2.0
Keywords: LD computing,Liftover,Region extraction
Platform: UNKNOWN
Classifier: Development Status :: 3 - Alpha
Classifier: Intended Audience :: Developers
Classifier: Natural Language :: English
Classifier: Programming Language :: Python :: 3.6
Classifier: Programming Language :: Python :: 3.7
Classifier: Programming Language :: Python :: 3.8
Classifier: License :: OSI Approved :: Apache Software License
Requires-Python: >=3.6
License-File: LICENSE
Requires-Dist: pip
Requires-Dist: packaging
Requires-Dist: torch
Requires-Dist: numpy
Requires-Dist: pandas
Requires-Dist: scipy
Requires-Dist: dask
Requires-Dist: bgen-reader
Requires-Dist: pandas-plink (==2.2.5)
Requires-Dist: liftover
Requires-Dist: Biopython
Requires-Dist: pybgen
Provides-Extra: dev
